{
  "$schema": "https://developer.microsoft.com/json-schemas/fabric/item/report/definition/visualContainer/2.4.0/schema.json",
  "name": "d9735ef51387e2caab42",
  "position": {
    "x": 253.12607944732298,
    "y": 19.896373056994818,
    "z": 0,
    "height": 84.006908462867017,
    "width": 237.65112262521589,
    "tabOrder": 0
  },
  "visual": {
    "visualType": "textbox",
    "objects": {
      "general": [
        {
          "properties": {
            "paragraphs": [
              {
                "textRuns": [
                  {
                    "value": "Maji Ndogo Water",
                    "textStyle": {
                      "fontSize": "20pt"
                    }
                  }
                ]
              },
              {
                "textRuns": [
                  {
                    "value": "National Water Survey Results"
                  }
                ]
              }
            ]
          }
        }
      ]
    },
    "drillFilterOtherVisuals": true
  }
}